rest/connector/__init__.py
rest/connector/implementation.py
rest/connector/utils.py
rest/connector/libs/__init__.py
rest/connector/libs/apic/__init__.py
rest/connector/libs/apic/acisdk_implementation.py
rest/connector/libs/apic/implementation.py
rest/connector/libs/bigip/__init__.py
rest/connector/libs/bigip/implementation.py
rest/connector/libs/dcnm/__init__.py
rest/connector/libs/dcnm/implementation.py
rest/connector/libs/dnac/__init__.py
rest/connector/libs/dnac/implementation.py
rest/connector/libs/elasticsearch/__init__.py
rest/connector/libs/elasticsearch/implementation.py
rest/connector/libs/iosxe/__init__.py
rest/connector/libs/iosxe/implementation.py
rest/connector/libs/ise/__init__.py
rest/connector/libs/ise/implementation.py
rest/connector/libs/nd/__init__.py
rest/connector/libs/nd/implementation.py
rest/connector/libs/nexusdashboard/__init__.py
rest/connector/libs/nexusdashboard/implementation.py
rest/connector/libs/nso/__init__.py
rest/connector/libs/nso/implementation.py
rest/connector/libs/nxos/__init__.py
rest/connector/libs/nxos/implementation.py
rest/connector/libs/nxos/aci/__init__.py
rest/connector/libs/nxos/aci/implementation.py
rest/connector/libs/viptela/__init__.py
rest/connector/libs/viptela/implementation.py
rest/connector/libs/virl/__init__.py
rest/connector/libs/virl/implementation.py
rest/connector/libs/vmware/__init__.py
rest/connector/libs/vmware/implementation.py
rest/connector/libs/webex/__init__.py
rest/connector/libs/webex/implementation.py
rest/connector/libs/xpresso/__init__.py
rest/connector/libs/xpresso/implementation.py
rest/connector/tests/__init__.py
rest/connector/tests/test_apic.py
rest/connector/tests/test_apic_cobra.py
rest/connector/tests/test_bigip.py
rest/connector/tests/test_elasticsearch.py
rest/connector/tests/test_iosxe.py
rest/connector/tests/test_ise.py
rest/connector/tests/test_nd.py
rest/connector/tests/test_nso.py
rest/connector/tests/test_nxos.py
rest/connector/tests/test_viptela.py
rest.connector-25.9.dist-info/METADATA
rest.connector-25.9.dist-info/WHEEL
rest.connector-25.9.dist-info/top_level.txt
rest.connector-25.9.dist-info/RECORD
