Metadata-Version: 2.1
Name: rest.connector
Version: 25.9
Summary: pyATS REST connection package
Home-page: https://developer.cisco.com/docs/rest-connector/
Author: Cisco Systems Inc.
Author-email: jeaubin@cisco.com
Maintainer-email: pyats-support-ext@cisco.com
License: Apache 2.0
Keywords: pyats cisco-shared
Platform: Linux
Platform: macOS
Classifier: Development Status :: 6 - Mature
Classifier: Development Status :: 5 - Production/Stable
Classifier: Environment :: Console
Classifier: Intended Audience :: Developers
Classifier: Intended Audience :: Telecommunications Industry
Classifier: Intended Audience :: Information Technology
Classifier: Intended Audience :: System Administrators
Classifier: License :: OSI Approved :: Apache Software License
Classifier: Operating System :: MacOS
Classifier: Operating System :: POSIX :: Linux
Classifier: Programming Language :: Python :: 3.7
Classifier: Programming Language :: Python :: 3.6
Classifier: Programming Language :: Python :: 3.5
Classifier: Programming Language :: Python :: 3 :: Only
Classifier: Programming Language :: Python :: Implementation :: CPython
Classifier: Topic :: Software Development :: Testing
Classifier: Topic :: Software Development :: Build Tools
Classifier: Topic :: Software Development :: Libraries
Classifier: Topic :: Software Development :: Libraries :: Python Modules
Requires-Dist: requests>=1.15.1
Requires-Dist: dict2xml
Requires-Dist: f5-icontrol-rest
Requires-Dist: ciscoisesdk
Provides-Extra: dev
Requires-Dist: coverage; extra == "dev"
Requires-Dist: restview; extra == "dev"
Requires-Dist: Sphinx; extra == "dev"
Requires-Dist: sphinx-rtd-theme; extra == "dev"
Requires-Dist: requests-mock; extra == "dev"
